googlenewspy/__init__.py
googlenewspy/exceptions.py
googlenewspy/maps.py
googlenewspy/parse.py
googlenewspy/regex.py
googlenewspy/search.py
googlenewspy/utils.py
tests/__init__.py
tests/test.py
googlenewspy-0.0.1.dist-info/LICENSE
googlenewspy-0.0.1.dist-info/METADATA
googlenewspy-0.0.1.dist-info/WHEEL
googlenewspy-0.0.1.dist-info/top_level.txt
googlenewspy-0.0.1.dist-info/RECORD
