Metadata-Version: 2.1
Name: googlenewspy
Version: 0.0.1
Summary: Scraping google news
Home-page: https://github.com/fernandoarrj/googlenewspy
Author: Fernando Rodrigues
Author-email: fernandoarrj@gmail.com
License: UNKNOWN
Platform: UNKNOWN
Classifier: Programming Language :: Python :: 3
Classifier: License :: OSI Approved :: MIT License
Classifier: Operating System :: OS Independent
Requires-Python: >=3.6
